tempstick_py/__about__.py
tempstick_py/__init__.py
tempstick_py/_helpers.py
tempstick_py/exceptions.py
tempstick_py/tempstick.py
tempstick_py-0.0.1b0.dev1.dist-info/METADATA
tempstick_py-0.0.1b0.dev1.dist-info/WHEEL
tempstick_py-0.0.1b0.dev1.dist-info/licenses/LICENSE
tempstick_py-0.0.1b0.dev1.dist-info/RECORD
